contextual_ner/__init__.py
contextual_ner/data/__init__.py
contextual_ner/data/camembert_ner_dataset.py
contextual_ner/data/make_quaero_dataset.py
contextual_ner/models/__init__.py
contextual_ner/models/camembert_for_token_classification.py
contextual_ner/models/camembert_ner_ft.py
contextual_ner/models/classifiers.py
contextual_ner/models/utils.py
contextual_ner/resources/__init__.py
contextual_ner/resources/log_config.ini
name_entity_extraction_for_contextual_embedding-0.41.0.dist-info/LICENSE
name_entity_extraction_for_contextual_embedding-0.41.0.dist-info/METADATA
name_entity_extraction_for_contextual_embedding-0.41.0.dist-info/WHEEL
name_entity_extraction_for_contextual_embedding-0.41.0.dist-info/entry_points.txt
name_entity_extraction_for_contextual_embedding-0.41.0.dist-info/top_level.txt
name_entity_extraction_for_contextual_embedding-0.41.0.dist-info/RECORD
