Metadata-Version: 2.1
Name: name-entity-extraction-for-contextual-embedding
Version: 0.41.0
Summary: a machine learning project for mlm task for contextual embedding
Home-page: UNKNOWN
Author: Simon Meoni
Author-email: UNKNOWN
License: MIT
Platform: UNKNOWN
Requires-Dist: click (==7.1.2)
Requires-Dist: pandas (==1.2.3)
Requires-Dist: python-dotenv (==0.15.0)
Requires-Dist: tokenizers (==0.10.1)
Requires-Dist: torch (==1.7.1)
Requires-Dist: wandb (==0.10.21)
Requires-Dist: numpy (==1.20.1)
Requires-Dist: sklearn (==0.0)
Requires-Dist: scikit-learn (==0.24.1)
Requires-Dist: transformers (==4.3.3)
